[
    {
        "courseLogo": "WEB",
        "courseName": "web前端实战教学",
        "courseTeacher": "龙华老师",
        "courseAddress": "广州市天河区体育西路1号天河城大厦18楼1801室",
        "score": 5,
        "bgColor": []
    },
    {
        "courseLogo": "UI",
        "courseName": "ui设计实战教学",
        "courseTeacher": "小美老师",
        "courseAddress": "广州市天河区体育西路1号天河城大厦18楼1802室",
        "score": 5,
        "bgColor": []
    },
    {
        "courseLogo": "NODE",
        "courseName": "node.js实战教学",
        "courseTeacher": "blue老师",
        "courseAddress": "广州市天河区体育西路1号天河城大厦18楼1803室",
        "score": 5,
        "bgColor": []
    },
    {
        "courseLogo": "PYTHON",
        "courseName": "Python实战教学",
        "courseTeacher": "黄明华老师",
        "courseAddress": "广州市天河区体育西路1号天河城大厦18楼1804室",
        "score": 5,
        "bgColor": []
    },
    {
        "courseLogo": "JAVA",
        "courseName": "java后端实战教学",
        "courseTeacher": "jeck老师",
        "courseAddress": "广州市天河区体育西路1号天河城大厦18楼1805室",
        "score": 5,
        "bgColor": []
    },
    {
        "courseLogo": "PHP",
        "courseName": "php后端实战教学",
        "courseTeacher": "陈龙老师",
        "courseAddress": "广州市天河区体育西路1号天河城大厦18楼1806室",
        "score": 5,
        "bgColor": []
    },
    {
        "courseLogo": "VUE",
        "courseName": "vue-MVVM框架",
        "courseTeacher": "沈桂琴老师",
        "courseAddress": "广州市天河区体育西路1号天河城大厦18楼1807室",
        "score": 5,
        "bgColor": []
    },
    {
        "courseLogo": "ANGULAR",
        "courseName": "angular实战app",
        "courseTeacher": "安娜老师",
        "courseAddress": "广州市天河区体育西路1号天河城大厦18楼1808室",
        "score": 5,
        "bgColor": []
    }
]